config_parser/__init__.py
config_parser/config_parser.py
config_parser/py.typed
PyConfigMaker-1.4.dist-info/LICENSE
PyConfigMaker-1.4.dist-info/METADATA
PyConfigMaker-1.4.dist-info/WHEEL
PyConfigMaker-1.4.dist-info/top_level.txt
PyConfigMaker-1.4.dist-info/RECORD
