Metadata-Version: 2.1
Name: PyConfigMaker
Version: 1.4
Summary: Generates a config and an argument parser from a yaml file
Home-page: https://github.com/cvoelcker/PyConfigMaker
Author: Claas Voelcker
Author-email: claas@voelcker.net
License: UNKNOWN
Platform: UNKNOWN
Requires-Dist: pyyaml
